alignt/__init__.py
alignt-0.1.0.dist-info/LICENSE
alignt-0.1.0.dist-info/METADATA
alignt-0.1.0.dist-info/WHEEL
alignt-0.1.0.dist-info/RECORD
